csv_pm_llm_parsing/__init__.py
csv_pm_llm_parsing/constants.py
csv_pm_llm_parsing/meta.py
csv_pm_llm_parsing/pm_columns_detection.py
csv_pm_llm_parsing/sep_detection.py
csv_pm_llm_parsing/timest_parser.py
csv_pm_llm_parsing/util.py
csv_pm_llm_parsing-0.1.dist-info/LICENSE
csv_pm_llm_parsing-0.1.dist-info/METADATA
csv_pm_llm_parsing-0.1.dist-info/WHEEL
csv_pm_llm_parsing-0.1.dist-info/top_level.txt
csv_pm_llm_parsing-0.1.dist-info/RECORD
