Metadata-Version: 2.1
Name: csv-pm-llm-parsing
Version: 0.1
Summary: LLM-based CSV parsing for Process Mining purposes
Home-page: https://github.com/fit-alessandro-berti/csv-pm-llm-parsing
Author: Alessandro Berti, PADS @ RWTH
Author-email: a.berti@pads.rwth-aachen.de
License: Apache 2.0
Project-URL: Documentation, https://github.com/fit-alessandro-berti/csv-pm-llm-parsing
Project-URL: Source, https://github.com/fit-alessandro-berti/csv-pm-llm-parsing
Project-URL: Tracker, https://github.com/fit-alessandro-berti/csv-pm-llm-parsing/issues
License-File: LICENSE
Requires-Dist: setuptools
Requires-Dist: numpy
Requires-Dist: pandas
Requires-Dist: requests
Requires-Dist: chardet
